[
  {
    "gpName": "云内动力",
    "selfTurnover": 149.66,
    "yesterdaySelfTurnover": 90.21,
    "formerAmPm": 0,
    "formerStartPoint": 0.91,
    "formerTopPoint": 9.45,
    "formerLowPoint": -4.57,
    "formerEndPoint": -3.66,
    "formerAveragePoint": 2.44,
    "latterStartPoint": 0.95,
    "latterTopPoint": 5.70,
    "latterLowPoint": -1.27,
    "latterEndPoint": 3.16,
    "latterAveragePoint": 1.90,
    "afterHigh": 5.70,
    "lastPrice": 0.71,
    "formerAllValue": 62.98,
    "formerDate": "2023-08-15"
  },
  {
    "gpName": "英飞拓",
    "formerDate": "2023-08-15",
    "formerAllValue": 92.82,
    "yesterdaySelfTurnover": 217.74,
    "selfTurnover": 147.56,
    "formerStartPoint": 2.71,
    "formerTopPoint": 8.00,
    "formerLowPoint": 0.34,
    "formerEndPoint": 2.82,
    "formerAveragePoint": 3.72,
    "latterStartPoint": 0.11,
    "latterTopPoint": 5.15,
    "latterLowPoint": -2.08,
    "latterEndPoint": 2.08,
    "latterAveragePoint": 0.66,
    "afterHigh": 5.15,
    "formerAmPm": 0,
    "lastPrice": 0.96
  },
  {
    "gpName": "南凌科技",
    "formerDate": "2023-08-15",
    "formerAllValue": 17.93,
    "yesterdaySelfTurnover": 217.74,
    "selfTurnover": 147.56,
    "formerStartPoint": 2.71,
    "formerTopPoint": 8.00,
    "formerLowPoint": 0.34,
    "formerEndPoint": 2.82,
    "formerAveragePoint": 3.72,
    "latterStartPoint": 0.11,
    "latterTopPoint": 5.15,
    "latterLowPoint": -2.08,
    "latterEndPoint": 2.08,
    "latterAveragePoint": 0.66,
    "afterHigh": 5.15,
    "formerAmPm": 0,
    "lastPrice": 0.68
  },
  {
    "gpName": "浙江震元",
    "formerDate": "2023-08-14",
    "formerAllValue": 26.05,
    "yesterdaySelfTurnover": 122.35,
    "selfTurnover": 323.65,
    "formerStartPoint": 3.14,
    "formerTopPoint": 8.12,
    "formerLowPoint": -0.22,
    "formerEndPoint": 0.97,
    "formerAveragePoint": 3.46,
    "latterStartPoint": -3.32,
    "latterTopPoint": 9.97,
    "latterLowPoint": -3.32,
    "latterEndPoint": 4.5,
    "latterAveragePoint": 2.89,
    "afterHigh": 9.97,
    "formerAmPm": 0,
    "lastPrice": 0.38
  },
  {
    "gpName": "麦趣尔",
    "formerDate": "2023-08-11",
    "formerAllValue": 21.92,
    "yesterdaySelfTurnover": 112.95,
    "selfTurnover": 154.06,
    "formerStartPoint": 3.99,
    "formerTopPoint": 7.09,
    "formerLowPoint": -1.99,
    "formerEndPoint": -1.99,
    "formerAveragePoint": 2.66,
    "latterStartPoint": 0.00,
    "latterTopPoint": 7.16,
    "latterLowPoint": -1.21,
    "latterEndPoint": 2.49,
    "latterAveragePoint": 2.71,
    "afterHigh": 7.16,
    "formerAmPm": 0,
    "lastPrice": 0.88
  },
  {
    "gpName": "贵州燃气",
    "formerDate": "2023-08-11",
    "formerAllValue": 107.03,
    "yesterdaySelfTurnover": 1166.15,
    "selfTurnover": 178.91,
    "formerStartPoint": 3.54,
    "formerTopPoint": 7.30,
    "formerLowPoint": 0.00,
    "formerEndPoint": 1.18,
    "formerAveragePoint": 2.69,
    "latterStartPoint": -0.11,
    "latterTopPoint": 0.00,
    "latterLowPoint": -3.82,
    "latterEndPoint": -2.65,
    "latterAveragePoint": -2.65,
    "afterHigh": 0.00,
    "formerAmPm": 1,
    "lastPrice": 0.57
  },
  {
    "gpName": "天地在线",
    "formerDate": "2023-08-11",
    "formerAllValue": 31.83,
    "yesterdaySelfTurnover": 158.39,
    "selfTurnover": 169.94,
    "formerStartPoint": 1.38,
    "formerTopPoint": 7.70,
    "formerLowPoint": -0.95,
    "formerEndPoint": 3.6,
    "formerAveragePoint": 2.61,
    "latterStartPoint": -5.28,
    "latterTopPoint": -1.30,
    "latterLowPoint": -7.19,
    "latterEndPoint": -1.33,
    "latterAveragePoint": -3.41,
    "afterHigh": 0.00,
    "formerAmPm": 0,
    "lastPrice": 0.47
  },
  {
    "gpName": "大理药业",
    "formerDate": "2023-08-10",
    "formerAllValue": 27.15,
    "yesterdaySelfTurnover": 202.86,
    "selfTurnover": 143.42,
    "formerStartPoint": 0.40,
    "formerTopPoint": 7.69,
    "formerLowPoint": -1.62,
    "formerEndPoint": 0,
    "formerAveragePoint": 2.35,
    "latterStartPoint": 1.13,
    "latterTopPoint": 5.58,
    "latterLowPoint": -2.51,
    "latterEndPoint": -2.35,
    "latterAveragePoint": 1.94,
    "afterHigh": 5.58,
    "formerAmPm": 0,
    "lastPrice": 0.6
  },
  {
    "gpName": "开开实业",
    "formerDate": "2023-08-10",
    "formerAllValue": 16.51,
    "yesterdaySelfTurnover": 795.78,
    "selfTurnover": 282.22,
    "formerStartPoint": 2.71,
    "formerTopPoint": 9.98,
    "formerLowPoint": 0.78,
    "formerEndPoint": 3.88,
    "formerAveragePoint": 5.72,
    "latterStartPoint": -3.73,
    "latterTopPoint": 9.98,
    "latterLowPoint": -5.60,
    "latterEndPoint": 9.98,
    "latterAveragePoint": 6.25,
    "afterHigh": 58,
    "formerAmPm": 0,
    "lastPrice": 0.54
  },
  {
    "gpName": "四环生物",
    "formerDate": "2023-08-10",
    "formerAllValue": 31.40,
    "yesterdaySelfTurnover": 413.05,
    "selfTurnover": 271.80,
    "formerStartPoint": 4.92,
    "formerTopPoint": 8.20,
    "formerLowPoint": 0.00,
    "formerEndPoint": 1.64,
    "formerAveragePoint": 4.26,
    "latterStartPoint": -1.29,
    "latterTopPoint": 2.26,
    "latterLowPoint": -2.90,
    "latterEndPoint": -2.58,
    "latterAveragePoint": -0.32,
    "afterHigh": 2.26,
    "formerAmPm": 0,
    "lastPrice": 1.52
  },
  {
    "gpName": "德展健康",
    "formerDate": "2023-08-10",
    "formerAllValue": 73.60,
    "yesterdaySelfTurnover": 401.25,
    "selfTurnover": 372.40,
    "formerStartPoint": 3.24,
    "formerTopPoint": 10.00,
    "formerLowPoint": 1.76,
    "formerEndPoint": 5.29,
    "formerAveragePoint": 5.88,
    "latterStartPoint": -4.75,
    "latterTopPoint": 5.31,
    "latterLowPoint": -6.15,
    "latterEndPoint": -1.12,
    "latterAveragePoint": 0.28,
    "afterHigh": 5.31,
    "formerAmPm": 0,
    "lastPrice": 0.68
  },
  {
    "gpName": "联合水务",
    "formerDate": "2023-08-10",
    "formerAllValue": 7.34,
    "yesterdaySelfTurnover": 556.09,
    "selfTurnover": 131.30,
    "formerStartPoint": -1.85,
    "formerTopPoint": 9.57,
    "formerLowPoint": -2.71,
    "formerEndPoint": 1.85,
    "formerAveragePoint": 1.79,
    "latterStartPoint": -0.34,
    "latterTopPoint": 3.79,
    "latterLowPoint": -2.10,
    "latterEndPoint": -1.81,
    "latterAveragePoint": -0.11,
    "afterHigh": 3.79,
    "formerAmPm": 0,
    "lastPrice": 0.11
  },
  {
    "gpName": "南天信息",
    "formerDate": "2023-08-10",
    "formerAllValue": 76.87,
    "yesterdaySelfTurnover": 481.08,
    "selfTurnover": 142.04,
    "formerStartPoint": -0.94,
    "formerTopPoint": 9.07,
    "formerLowPoint": -3.07,
    "formerEndPoint": 1.93,
    "formerAveragePoint": 1.93,
    "latterStartPoint": -2.43,
    "latterTopPoint": -1.07,
    "latterLowPoint": -5.16,
    "latterEndPoint": -3.21,
    "latterAveragePoint": -3.40,
    "afterHigh": 0,
    "formerAmPm": 1,
    "lastPrice": 1.27
  },
  {
    "gpName": "威奥股份",
    "formerDate": "2023-08-09",
    "formerAllValue": 29.62,
    "yesterdaySelfTurnover": 118.39,
    "selfTurnover": 372.31,
    "formerStartPoint": 2.12,
    "formerTopPoint": 8.49,
    "formerLowPoint": 0.53,
    "formerEndPoint": 2.92,
    "formerAveragePoint": 3.32,
    "latterStartPoint": -2.71,
    "latterTopPoint": 0.64,
    "latterLowPoint": -4.25,
    "latterEndPoint": 0.26,
    "latterAveragePoint": -1.93,
    "afterHigh": 0,
    "formerAmPm": 0,
    "lastPrice": 0.65
  },
  {
    "gpName": "中化岩土",
    "formerDate": "2023-08-09",
    "formerAllValue": 48.99,
    "yesterdaySelfTurnover": 662.16,
    "selfTurnover": 211.35,
    "formerStartPoint": 3.57,
    "formerTopPoint": 8.12,
    "formerLowPoint": -3.25,
    "formerEndPoint": -2.92,
    "formerAveragePoint": 7.47,
    "latterStartPoint": -1.34,
    "latterTopPoint": 0.67,
    "latterLowPoint": -3.34,
    "latterEndPoint": -2.68,
    "latterAveragePoint": -2.01,
    "afterHigh": 0,
    "formerAmPm": 0,
    "lastPrice": 2.02
  },
  {
    "gpName": "龙津药业",
    "formerDate": "2023-08-09",
    "formerAllValue": 40.26,
    "yesterdaySelfTurnover": 285.07,
    "selfTurnover": 273.28,
    "formerStartPoint": 1.88,
    "formerTopPoint": 8.21,
    "formerLowPoint": 1.29,
    "formerEndPoint": 2.87,
    "formerAveragePoint": 4.15,
    "latterStartPoint": 0.67,
    "latterTopPoint": 1.44,
    "latterLowPoint": -1.25,
    "latterEndPoint": -0.1,
    "latterAveragePoint": -0.48,
    "afterHigh": 1.44,
    "formerAmPm": 0,
    "lastPrice": 0.5
  },
  {
    "gpName": "精华制药",
    "formerDate": "2023-08-09",
    "formerAllValue": 81.70,
    "yesterdaySelfTurnover": 329.22,
    "selfTurnover": 208.73,
    "formerStartPoint": 2.38,
    "formerTopPoint": 8.04,
    "formerLowPoint": 1.79,
    "formerEndPoint": 3.87,
    "formerAveragePoint": 4.57,
    "latterStartPoint": -0.86,
    "latterTopPoint": 1.34,
    "latterLowPoint": -2.68,
    "latterEndPoint": -1.15,
    "latterAveragePoint": -0.86,
    "afterHigh": 1.34,
    "formerAmPm": 0,
    "lastPrice": 1.23
  }
]